[
  {
    "Team": "Jono",
    "Points": 867,
    "Games Played": 51,
    "PPG": 17.0
  },
  {
    "Team": "Julian",
    "Points": 1263,
    "Games Played": 55,
    "PPG": 22.96
  },
  {
    "Team": "Sam",
    "Points": 1276,
    "Games Played": 76,
    "PPG": 16.79
  },
  {
    "Team": "Andrew",
    "Points": 902,
    "Games Played": 53,
    "PPG": 17.02
  },
  {
    "Team": "Joe",
    "Points": 1327,
    "Games Played": 73,
    "PPG": 18.18
  },
  {
    "Team": "Connor",
    "Points": 1012,
    "Games Played": 62,
    "PPG": 16.32
  }
]